AUTHORS
ChangeLog
LICENSE
Readme.rst
requirements.txt
setup.cfg
setup.py
tox.ini
docker_cleaner/__init__.py
docker_cleaner/auto_cleaner.py
docker_cleaner/logger.py
docker_cleaner/main.py
docker_cleaner.egg-info/PKG-INFO
docker_cleaner.egg-info/SOURCES.txt
docker_cleaner.egg-info/dependency_links.txt
docker_cleaner.egg-info/entry_points.txt
docker_cleaner.egg-info/not-zip-safe
docker_cleaner.egg-info/pbr.json
docker_cleaner.egg-info/requires.txt
docker_cleaner.egg-info/top_level.txt