Metadata-Version: 1.1
Name: docker-cleaner
Version: 1.3.0
Summary: This utility is designed for cleaning up docker resources.
Home-page: https://github.com/FromZeus/docker-cleaner
Author: Daniil Trishkin
Author-email: asteroid566@gmail.com
License: UNKNOWN
Platform: UNKNOWN
Classifier: Intended Audience :: Information Technology
Classifier: Intended Audience :: System Administrators
Classifier: License :: OSI Approved :: Apache Software License
Classifier: Operating System :: POSIX :: Linux
Classifier: Programming Language :: Python
Classifier: Programming Language :: Python :: 2
Classifier: Programming Language :: Python :: 2.7
